kalendar/__init__.py
kalendar/_version.py
kalendar/dekad.py
kalendar/pentad.py
kalendar-0.1.1.dist-info/LICENSE
kalendar-0.1.1.dist-info/METADATA
kalendar-0.1.1.dist-info/WHEEL
kalendar-0.1.1.dist-info/top_level.txt
kalendar-0.1.1.dist-info/RECORD
