Metadata-Version: 2.1
Name: kalendar
Version: 0.1.1
Summary: Datetime extensions for dekadal data
Home-page: https://github.com/OCHA-DAP/kalendar
Author: Seth Caldwell
Author-email: caldwellst@gmail.com
License: GPLv3
Project-URL: Documentation, https://kalendar.readthedocs.io/en/latest/
Project-URL: Changes, https://github.com/OCHA-DAP/pa-aa-toolbox/blob/main/CHANGELOG.rst
Project-URL: PyPI Releases, https://pypi.org/project/kalendar/
Project-URL: Source Code, https://github.com/OCHA-DAP/kalendar/
Project-URL: Issue Tracker, https://github.com/OCHA-DAP/kalendar/issues/
Classifier: Development Status :: 3 - Alpha
Classifier: Intended Audience :: Developers
Classifier: Intended Audience :: Science/Research
Classifier: License :: OSI Approved :: GNU General Public License v3 (GPLv3)
Classifier: Natural Language :: English
Classifier: Operating System :: OS Independent
Classifier: Programming Language :: Python :: 3 :: Only
Requires-Python: >=3.8
License-File: LICENSE
Provides-Extra: dev
Requires-Dist: pytest ; extra == 'dev'
Requires-Dist: pytest-cov ; extra == 'dev'
Requires-Dist: tox ; extra == 'dev'
Requires-Dist: extras-require ; extra == 'dev'
Requires-Dist: sphinx ; extra == 'dev'
Requires-Dist: sphinx-rtd-theme ; extra == 'dev'
Requires-Dist: pre-commit ; extra == 'dev'
Provides-Extra: doc
Requires-Dist: extras-require ; extra == 'doc'
Requires-Dist: sphinx ; extra == 'doc'
Requires-Dist: sphinx-rtd-theme ; extra == 'doc'
Provides-Extra: test
Requires-Dist: pytest ; extra == 'test'
Requires-Dist: pytest-cov ; extra == 'test'
Requires-Dist: tox ; extra == 'test'
